jureqex/__init__.py
jureqex/requirement_extractor.py
jureqex-0.1.1.dist-info/LICENSE
jureqex-0.1.1.dist-info/METADATA
jureqex-0.1.1.dist-info/WHEEL
jureqex-0.1.1.dist-info/entry_points.txt
jureqex-0.1.1.dist-info/top_level.txt
jureqex-0.1.1.dist-info/RECORD
