Metadata-Version: 2.1
Name: jureqex
Version: 0.1.1
Summary: A package to exteact the requirements from a Jupyter notebook in a smart way.
Author-email: Iván Hidalgo <ivanhcenalmor@gmail.com>
Project-URL: Homepage, https://github.com/IvanHCenalmor/JupyterReqExtractor
Project-URL: Bug Tracker, https://github.com/IvanHCenalmor/JupyterReqExtractor/issues
Classifier: Programming Language :: Python :: 3
Classifier: License :: OSI Approved :: Apache Software License
Requires-Python: >=3.7
License-File: LICENSE
Requires-Dist: nbformat
Requires-Dist: yarg
